README.md
setup.py
mfpfile/__init__.py
mfpfile/mfpfile.py
mfpfile.egg-info/PKG-INFO
mfpfile.egg-info/SOURCES.txt
mfpfile.egg-info/dependency_links.txt
mfpfile.egg-info/entry_points.txt
mfpfile.egg-info/not-zip-safe
mfpfile.egg-info/requires.txt
mfpfile.egg-info/top_level.txt