Metadata-Version: 1.0
Name: mfpfile
Version: 1.1
Summary: Package to handle reading of ibw files created with MFP devices.
Home-page: UNKNOWN
Author: Ilyas Kuhlemann
Author-email: ilyasp.ku@gmail.com
License: MIT
Platform: UNKNOWN
